flake8_keyword_arguments/__init__.py
flake8_keyword_arguments/checker.py
flake8_keyword_arguments/utils.py
tests/__init__.py
tests/conftest.py
tests/test_plugin.py
flake8_keyword_arguments-0.1.0.dist-info/LICENSE.md
flake8_keyword_arguments-0.1.0.dist-info/METADATA
flake8_keyword_arguments-0.1.0.dist-info/WHEEL
flake8_keyword_arguments-0.1.0.dist-info/entry_points.txt
flake8_keyword_arguments-0.1.0.dist-info/top_level.txt
flake8_keyword_arguments-0.1.0.dist-info/RECORD
