Metadata-Version: 2.1
Name: flake8-keyword-arguments
Version: 0.1.0
Summary: A flake8 extension that is looking for function calls and forces to use keyword arguments if there are more than X arguments
Home-page: https://github.com/vchaptsev/flake8-keyword-arguments
Author: Viktor Chaptsev
Author-email: viktor@chaptsev.ru
License: MIT
Keywords: flake8
Platform: UNKNOWN
Classifier: Environment :: Console
Classifier: Framework :: Flake8
Classifier: Operating System :: OS Independent
Classifier: Topic :: Software Development :: Documentation
Classifier: Topic :: Software Development :: Libraries :: Python Modules
Classifier: Topic :: Software Development :: Quality Assurance
Classifier: Programming Language :: Python
Classifier: Programming Language :: Python :: 3.6
Classifier: Programming Language :: Python :: 3.7
Classifier: Programming Language :: Python :: 3.8
Requires-Python: >=3.6
Requires-Dist: flake8
Requires-Dist: setuptools
Requires-Dist: typing-extensions
